kaos/__init__.py
kaos/callbacks.py
kaos/distributions.py
kaos/exponential.py
kaos/ladder.py
kaos/nputils.py
kaos/scripts.py
kaos/softplus.py
kaos/utils.py
kaos/bayes/__init__.py
kaos/bayes/core.py
kaos/data/__init__.py
kaos/data/data_loader.py
kaos/layers/__init__.py
kaos/layers/merge.py
kaos/layers/normalization.py
kaos-0.1.dist-info/DESCRIPTION.rst
kaos-0.1.dist-info/METADATA
kaos-0.1.dist-info/RECORD
kaos-0.1.dist-info/WHEEL
kaos-0.1.dist-info/entry_points.txt
kaos-0.1.dist-info/metadata.json
kaos-0.1.dist-info/top_level.txt
