Metadata-Version: 2.0
Name: kaos
Version: 0.1
Summary: a library designed to simplify the building of deep amortized inference models
Home-page: http://www.github.com/RuiShu/kaos
Author: Rui Shu
Author-email: ruishu@stanford.edu
License: LICENSE.md
Keywords: keras deep learning
Platform: UNKNOWN
Requires-Dist: keras
Requires-Dist: numpy
